evalscope/__init__.py
evalscope/arguments.py
evalscope/config.py
evalscope/constants.py
evalscope/run.py
evalscope/version.py
evalscope/api/__init__.py
evalscope/api/registry.py
evalscope/api/benchmark/__init__.py
evalscope/api/benchmark/benchmark.py
evalscope/api/benchmark/meta.py
evalscope/api/benchmark/adapters/__init__.py
evalscope/api/benchmark/adapters/agent_adapter.py
evalscope/api/benchmark/adapters/default_data_adapter.py
evalscope/api/benchmark/adapters/image_edit_adapter.py
evalscope/api/benchmark/adapters/multi_choice_adapter.py
evalscope/api/benchmark/adapters/ner_adapter.py
evalscope/api/benchmark/adapters/text2image_adapter.py
evalscope/api/benchmark/adapters/vision_language_adapter.py
evalscope/api/dataset/__init__.py
evalscope/api/dataset/dataset.py
evalscope/api/dataset/loader.py
evalscope/api/dataset/utils.py
evalscope/api/evaluator/__init__.py
evalscope/api/evaluator/cache.py
evalscope/api/evaluator/evaluator.py
evalscope/api/evaluator/state.py
evalscope/api/filter/__init__.py
evalscope/api/filter/filter.py
evalscope/api/messages/__init__.py
evalscope/api/messages/chat_message.py
evalscope/api/messages/content.py
evalscope/api/messages/utils.py
evalscope/api/metric/__init__.py
evalscope/api/metric/metric.py
evalscope/api/metric/scorer.py
evalscope/api/mixin/__init__.py
evalscope/api/mixin/llm_judge_mixin.py
evalscope/api/mixin/sandbox_mixin.py
evalscope/api/model/__init__.py
evalscope/api/model/generate_config.py
evalscope/api/model/lazy_model.py
evalscope/api/model/model.py
evalscope/api/model/model_output.py
evalscope/api/tool/__init__.py
evalscope/api/tool/tool_call.py
evalscope/api/tool/tool_info.py
evalscope/api/tool/utils.py
evalscope/app/__init__.py
evalscope/app/app.py
evalscope/app/arguments.py
evalscope/app/constants.py
evalscope/app/ui/__init__.py
evalscope/app/ui/app_ui.py
evalscope/app/ui/multi_model.py
evalscope/app/ui/sidebar.py
evalscope/app/ui/single_model.py
evalscope/app/ui/visualization.py
evalscope/app/utils/data_utils.py
evalscope-1.4.2.dist-info/licenses/LICENSE
evalscope-1.4.2.dist-info/METADATA
evalscope-1.4.2.dist-info/WHEEL
evalscope-1.4.2.dist-info/entry_points.txt
evalscope-1.4.2.dist-info/top_level.txt
evalscope-1.4.2.dist-info/RECORD
