Metadata-Version: 2.4
Name: evalscope
Version: 1.4.2
Summary: EvalScope: Lightweight LLMs Evaluation Framework
Author: ModelScope team
Author-email: contact@modelscope.cn
License: Apache License 2.0
Project-URL: Homepage, https://github.com/modelscope/evalscope
Keywords: python,llm,evaluation
Classifier: Development Status :: 4 - Beta
Classifier: Operating System :: OS Independent
Classifier: Programming Language :: Python :: 3
Classifier: Programming Language :: Python :: 3.10
Classifier: Programming Language :: Python :: 3.11
Classifier: Programming Language :: Python :: 3.12
Classifier: License :: OSI Approved :: Apache Software License
Requires-Python: >=3.10
License-File: LICENSE
Requires-Dist: colorlog
Requires-Dist: datasets==3.6.0
Requires-Dist: docstring_parser
Requires-Dist: dotenv
Requires-Dist: editdistance
Requires-Dist: jieba
Requires-Dist: jsonlines
Requires-Dist: jsonschema
Requires-Dist: langdetect
Requires-Dist: latex2sympy2_extended[antlr4_9_3]
Requires-Dist: matplotlib
Requires-Dist: modelscope[datasets,framework]>=1.27
Requires-Dist: more_itertools
Requires-Dist: nltk>=3.9
Requires-Dist: openai
Requires-Dist: overrides
Requires-Dist: pandas
Requires-Dist: pillow
Requires-Dist: pydantic
Requires-Dist: pylatexenc
Requires-Dist: pyyaml>=5.1
Requires-Dist: requests
Requires-Dist: rich
Requires-Dist: rouge-chinese
Requires-Dist: rouge-score>=0.1.0
Requires-Dist: sacrebleu
Requires-Dist: scikit-learn
Requires-Dist: seaborn
Requires-Dist: sympy
Requires-Dist: tabulate
Requires-Dist: tiktoken
Requires-Dist: tqdm
Requires-Dist: transformers!=4.57.2,>=4.33
Requires-Dist: word2number
Requires-Dist: zhconv
Provides-Extra: opencompass
Requires-Dist: ms-opencompass>=0.1.6; extra == "opencompass"
Provides-Extra: vlmeval
Requires-Dist: ms-vlmeval>=0.0.17; extra == "vlmeval"
Provides-Extra: rag
Requires-Dist: langchain<0.4.0,>=0.3.0; extra == "rag"
Requires-Dist: langchain-community<0.4.0,>=0.3.0; extra == "rag"
Requires-Dist: langchain-core<0.4.0,>=0.3.0; extra == "rag"
Requires-Dist: langchain-openai<0.4.0,>=0.3.0; extra == "rag"
Requires-Dist: mteb==1.38.20; extra == "rag"
Requires-Dist: ragas==0.2.14; extra == "rag"
Requires-Dist: torch; extra == "rag"
Requires-Dist: webdataset>0.2.0; extra == "rag"
Provides-Extra: perf
Requires-Dist: aiohttp; extra == "perf"
Requires-Dist: fastapi; extra == "perf"
Requires-Dist: jinja2; extra == "perf"
Requires-Dist: numpy; extra == "perf"
Requires-Dist: rich; extra == "perf"
Requires-Dist: sse_starlette; extra == "perf"
Requires-Dist: transformers; extra == "perf"
Requires-Dist: uvicorn; extra == "perf"
Provides-Extra: app
Requires-Dist: gradio==5.4.0; extra == "app"
Requires-Dist: plotly<6.0.0,>=5.23.0; extra == "app"
Provides-Extra: aigc
Requires-Dist: diffusers; extra == "aigc"
Requires-Dist: iopath; extra == "aigc"
Requires-Dist: omegaconf; extra == "aigc"
Requires-Dist: open_clip_torch; extra == "aigc"
Requires-Dist: opencv-python; extra == "aigc"
Requires-Dist: peft>=0.17; extra == "aigc"
Requires-Dist: torch; extra == "aigc"
Requires-Dist: torchvision; extra == "aigc"
Provides-Extra: sandbox
Requires-Dist: ms-enclave[docker]; extra == "sandbox"
Provides-Extra: service
Requires-Dist: flask>=2.0.0; extra == "service"
Provides-Extra: dev
Requires-Dist: pytest; extra == "dev"
Requires-Dist: pytest-cov; extra == "dev"
Requires-Dist: python-dotenv; extra == "dev"
Provides-Extra: docs
Requires-Dist: docutils>=0.16.0; extra == "docs"
Requires-Dist: myst_parser; extra == "docs"
Requires-Dist: recommonmark; extra == "docs"
Requires-Dist: sphinx>=5.3.0; extra == "docs"
Requires-Dist: sphinx-design; extra == "docs"
Requires-Dist: sphinxawesome-theme; extra == "docs"
Provides-Extra: all
Requires-Dist: ms-opencompass>=0.1.6; extra == "all"
Requires-Dist: ms-vlmeval>=0.0.17; extra == "all"
Requires-Dist: langchain<0.4.0,>=0.3.0; extra == "all"
Requires-Dist: langchain-community<0.4.0,>=0.3.0; extra == "all"
Requires-Dist: langchain-core<0.4.0,>=0.3.0; extra == "all"
Requires-Dist: langchain-openai<0.4.0,>=0.3.0; extra == "all"
Requires-Dist: mteb==1.38.20; extra == "all"
Requires-Dist: ragas==0.2.14; extra == "all"
Requires-Dist: torch; extra == "all"
Requires-Dist: webdataset>0.2.0; extra == "all"
Requires-Dist: aiohttp; extra == "all"
Requires-Dist: fastapi; extra == "all"
Requires-Dist: jinja2; extra == "all"
Requires-Dist: numpy; extra == "all"
Requires-Dist: rich; extra == "all"
Requires-Dist: sse_starlette; extra == "all"
Requires-Dist: transformers; extra == "all"
Requires-Dist: uvicorn; extra == "all"
Requires-Dist: gradio==5.4.0; extra == "all"
Requires-Dist: plotly<6.0.0,>=5.23.0; extra == "all"
Requires-Dist: diffusers; extra == "all"
Requires-Dist: iopath; extra == "all"
Requires-Dist: omegaconf; extra == "all"
Requires-Dist: open_clip_torch; extra == "all"
Requires-Dist: opencv-python; extra == "all"
Requires-Dist: peft>=0.17; extra == "all"
Requires-Dist: torch; extra == "all"
Requires-Dist: torchvision; extra == "all"
Requires-Dist: flask>=2.0.0; extra == "all"
Dynamic: license-file
